{
  "weather": [
    "weather"
  ],
  "softwarecenter": [
    "softwarecenter"
  ],
  "spotify": [
    "spotify"
  ],
  "gmail-2": [
    "gmail"
  ],
  "transmission": [
    "transmission"
  ],
  "google-drive": [
    "google",
    "drive",
    "browser"
  ],
  "system-software-update": [
    "software",
    "system",
    "app",
    "application",
    "edit",
    "pencil",
    "update"
  ],
  "birdie": [
    "birdie"
  ],
  "filezilla": [
    "filezilla"
  ],
  "gmail": [
    "gmail"
  ],
  "behance": [
    "behance"
  ],
  "multimedia-audio-player": [
    "audio",
    "multimedia",
    "music",
    "sound",
    "player"
  ],
  "synaptic": [
    "synaptic"
  ],
  "mega-cloud": [
    "mega",
    "cloudy",
    "cloud",
    "decrease",
    "down",
    "weather",
    "arrow"
  ],
  "virtualbox": [
    "virtualbox"
  ],
  "teamviewer": [
    "teamviewer"
  ],
  "hangouts": [
    "hangouts"
  ],
  "flickr": [
    "flickr",
    "social",
    "logo"
  ],
  "wunderlist": [
    "wunderlist"
  ],
  "darktable": [
    "darktable"
  ],
  "accessories-text-editor": [
    "accessories",
    "text",
    "editor",
    "edit",
    "pencil",
    "update"
  ],
  "empathy": [
    "empathy"
  ],
  "pidgin": [
    "pidgin"
  ],
  "steam": [
    "steam"
  ],
  "google-keep": [
    "google",
    "keep",
    "browser"
  ],
  "gloobus-preview": [
    "gloobus",
    "preview"
  ],
  "utilities-system-monitor": [
    "utilities",
    "tool",
    "utils",
    "system",
    "display",
    "konsole",
    "lcd",
    "screen",
    "terminal",
    "workstation",
    "monitor",
    "control",
    "hardware"
  ],
  "alarm-clock": [
    "alarm",
    "alert",
    "clock",
    "timer"
  ],
  "multimedia-video-player": [
    "multimedia",
    "film",
    "movie",
    "video",
    "player"
  ],
  "preferences-desktop": [
    "desk",
    "desktop",
    "preferences",
    "prefs"
  ],
  "google-plus": [
    "google",
    "plus",
    "browser"
  ],
  "skype": [
    "skype",
    "social",
    "logo"
  ],
  "cloud": [
    "cloud",
    "cloudy",
    "weather"
  ],
  "easytag": [
    "easytag"
  ],
  "midori": [
    "midori"
  ],
  "pinterest": [
    "pinterest"
  ],
  "utilities-terminal": [
    "tool",
    "utilities",
    "utils",
    "display",
    "konsole",
    "lcd",
    "monitor",
    "screen",
    "terminal",
    "workstation",
    "control",
    "hardware"
  ],
  "deja-dup": [
    "deja",
    "dup"
  ],
  "shotwell": [
    "shotwell"
  ],
  "evince": [
    "evince"
  ],
  "play-playstore": [
    "play",
    "playstore"
  ],
  "email": [
    "mail",
    "email",
    "contact"
  ],
  "amazon": [
    "amazon"
  ],
  "netbeans": [
    "netbeans"
  ],
  "rss-news-reader": [
    "rss",
    "news",
    "reader",
    "social",
    "logo"
  ],
  "steam-2": [
    "steam"
  ],
  "gimp": [
    "gimp"
  ],
  "browser-firefox": [
    "browser",
    "firefox"
  ],
  "inkscape": [
    "inkscape"
  ],
  "sublime-text": [
    "sublime",
    "text"
  ],
  "browser-chromium": [
    "browser",
    "chromium"
  ],
  "soundcloud": [
    "soundcloud"
  ],
  "deluge": [
    "deluge"
  ],
  "browser-google-chrome": [
    "browser",
    "chrome",
    "google"
  ],
  "pocket": [
    "pocket"
  ],
  "twitter": [
    "twitter",
    "social",
    "logo"
  ],
  "file-zipper": [
    "doc",
    "document",
    "file",
    "zipper",
    "paper"
  ],
  "system-software-installer": [
    "application",
    "system",
    "app",
    "software",
    "installer"
  ],
  "preferences": [
    "preferences",
    "prefs"
  ],
  "ubuntuone": [
    "ubuntuone"
  ],
  "eclipse": [
    "eclipse"
  ],
  "jdownloader": [
    "jdownloader"
  ],
  "accessories-calculator": [
    "accessories",
    "calc",
    "calculator"
  ],
  "system-file-manager": [
    "system",
    "doc",
    "document",
    "file",
    "manager",
    "paper"
  ],
  "office-calendar": [
    "event",
    "office",
    "calendar",
    "date",
    "organizer",
    "microsoft"
  ],
  "youtube": [
    "youtube",
    "social",
    "logo"
  ],
  "nvidia-settings": [
    "conf",
    "config",
    "configuration",
    "configure",
    "customise",
    "customization",
    "nvidia",
    "setting",
    "developer",
    "development",
    "settings"
  ],
  "dropbox": [
    "dropbox"
  ],
  "slingscold": [
    "slingscold"
  ],
  "nitro": [
    "nitro"
  ],
  "xnoise": [
    "xnoise"
  ],
  "vimeo": [
    "vimeo",
    "social",
    "logo"
  ],
  "grooveshark": [
    "grooveshark"
  ],
  "evernote": [
    "evernote"
  ],
  "adobe-reader": [
    "adobe",
    "reader"
  ],
  "synapse": [
    "synapse"
  ],
  "camera": [
    "cam",
    "camera",
    "hardware",
    "image",
    "photo",
    "photography",
    "picture"
  ],
  "nuvolaplayer": [
    "nuvolaplayer"
  ],
  "feedly": [
    "feedly"
  ],
  "brackets": [
    "brackets"
  ]
}